vtx_common/__init__.py
vtx_common/utils.py
vtx_common/version.py
vtx_common/tests/__init__.py
vtx_common/tests/common.py
vtx_common/tests/test_buildpkg.py
vtx_common/tests/test_get_pkg_syn_minver.py
vtx_common/tests/test_github_release.py
vtx_common/tests/test_utils.py
vtx_common/tools/__init__.py
vtx_common/tools/buildpkg.py
vtx_common/tools/get_pkg_syn_minver.py
vtx_common/tools/github_release.py
vtx_common/tools/pandoc_filter.py
vtx_common/tools/pep8_staged_files.py
vtx_common/tools/pre_commit.py
vtx_common/tools/replace_commit.py
vtx_common/tools/verify_version.py
vtx_common-0.2.1.dist-info/LICENSE
vtx_common-0.2.1.dist-info/METADATA
vtx_common-0.2.1.dist-info/WHEEL
vtx_common-0.2.1.dist-info/top_level.txt
vtx_common-0.2.1.dist-info/RECORD
