Metadata-Version: 2.1
Name: vtx-common
Version: 0.2.1
Summary: Vertex project tools to assist with packaging.
Home-page: https://github.com/vertexproject/common-tools
Author: The Vertex Project LLC
Author-email: epiphyte+tools@vertex.link
License: Apache License 2.0
Classifier: Development Status :: 4 - Beta
Classifier: License :: OSI Approved :: Apache Software License
Classifier: Topic :: System :: Clustering
Classifier: Topic :: System :: Distributed Computing
Classifier: Topic :: System :: Software Distribution
Classifier: Programming Language :: Python :: 3.11
Requires-Python: >=3.11
License-File: LICENSE
Requires-Dist: PyGithub<3.0.0,>=2.8.1
Requires-Dist: PyYAML
Requires-Dist: bump2version<2.0.0,>=1.0.1
Requires-Dist: pytest
Requires-Dist: autopep8
Requires-Dist: pytest-cov
Requires-Dist: pycodestyle
Requires-Dist: pytest-xdist
Provides-Extra: synapse
Requires-Dist: synapse<3.0.0,>=2.115.1; extra == "synapse"
